staticdirindex/__init__.py
staticdirindex/templates/index.html
staticdirindex/templates/sitemap.xml
staticdirindex-1.11.dist-info/LICENSE
staticdirindex-1.11.dist-info/METADATA
staticdirindex-1.11.dist-info/WHEEL
staticdirindex-1.11.dist-info/entry_points.txt
staticdirindex-1.11.dist-info/top_level.txt
staticdirindex-1.11.dist-info/RECORD
