Metadata-Version: 2.1
Name: staticdirindex
Version: 1.11
Summary: recursive directory listings with thumbnails
Home-page: https://github.com/swantzter/staticdirindex
Author: Svante Bengtson
Author-email: svante@swantzter.se
License: MIT
Classifier: Development Status :: 5 - Production/Stable
Classifier: Intended Audience :: Developers
Classifier: License :: OSI Approved :: MIT License
Classifier: Programming Language :: Python :: 3
License-File: LICENSE
Requires-Dist: gitignore-parser
Requires-Dist: preview-generator
Requires-Dist: mako
